tedutil/__init__.py
tedutil/dec.py
tedutil/fixed_size_file.py
tedutil/grdate.py
tedutil/grtext.py
tedutil/payroll.py
tedutil/taxes.py
tedutil/validators.py
tedutil-0.15.0.dist-info/LICENSE
tedutil-0.15.0.dist-info/METADATA
tedutil-0.15.0.dist-info/WHEEL
tedutil-0.15.0.dist-info/top_level.txt
tedutil-0.15.0.dist-info/RECORD
